MANIFEST.in
README.rst
setup.py
magento/__init__.py
magento/api.py
magento/catalog.py
magento/checkout.py
magento/customer.py
magento/directory.py
magento/miscellaneous.py
magento/rest.py
magento/sales.py
magento/utils.py
magento/version.py
magento.egg-info/PKG-INFO
magento.egg-info/SOURCES.txt
magento.egg-info/dependency_links.txt
magento.egg-info/not-zip-safe
magento.egg-info/requires.txt
magento.egg-info/top_level.txt